py_xsv/__init__.py
py_xsv-0.0.2.dist-info/METADATA
py_xsv-0.0.2.dist-info/WHEEL
py_xsv-0.0.2.dist-info/licenses/LICENSE
py_xsv-0.0.2.dist-info/RECORD
