Metadata-Version: 2.4
Name: py-xsv
Version: 0.0.2
Summary: Reading -sv files and writing them to dataframes
Author: someone624
License-Expression: WTFPL
License-File: LICENSE
Keywords: csv,data,parsing,tsv
Classifier: Development Status :: 4 - Beta
Classifier: License :: Public Domain
Classifier: Operating System :: OS Independent
Classifier: Programming Language :: Python :: 3.13
Requires-Python: >=3.9
